{
	"configurations" : 
	[
		{
			"directories" : 
			[
				{
					"build" : ".",
					"jsonFile" : "directory-.-Debug-f5ebdc15457944623624.json",
					"minimumCMakeVersion" : 
					{
						"string" : "3.26"
					},
					"projectIndex" : 0,
					"source" : ".",
					"targetIndexes" : 
					[
						0
					]
				}
			],
			"name" : "Debug",
			"projects" : 
			[
				{
					"directoryIndexes" : 
					[
						0
					],
					"name" : "240__Search_a_2D_Matrix_II_",
					"targetIndexes" : 
					[
						0
					]
				}
			],
			"targets" : 
			[
				{
					"directoryIndex" : 0,
					"id" : "240__Search_a_2D_Matrix_II_::@6890427a1f51a3e7e1df",
					"jsonFile" : "target-240__Search_a_2D_Matrix_II_-Debug-5987fc79210f788e0553.json",
					"name" : "240__Search_a_2D_Matrix_II_",
					"projectIndex" : 0
				}
			]
		}
	],
	"kind" : "codemodel",
	"paths" : 
	{
		"build" : "/home/sohaib/Desktop/letcode/240. Search a 2D Matrix II /cmake-build-debug",
		"source" : "/home/sohaib/Desktop/letcode/240. Search a 2D Matrix II "
	},
	"version" : 
	{
		"major" : 2,
		"minor" : 5
	}
}
